{"_type":"export","__export_format":4,"__export_date":"2020-09-09T06:02:41.479Z","__export_source":"insomnia.desktop.app:v2020.3.3","resources":[{"_id":"req_502363ec128d4a89b46eb5264be13337","authentication":{},"body":{"mimeType":"multipart/form-data","params":[]},"created":1599628424484,"description":"","headers":[{"description":"","id":"pair_239a253754014c33a218370d28890fe1","name":"post_id","value":"5f53a239f130bf002174ddf5"},{"description":"","id":"pair_235d670db28f44f6b8d9ec250184d537","name":"token","value":"5f5191422a9c66002141485b"}],"isPrivate":false,"metaSortKey":-1598563163532.5,"method":"POST","modified":1599629785818,"name":"CreateLike","parameters":[],"parentId":"fld_f2bc13ef05c94620a5f27e82b321a135","settingDisableRenderRequestBody":false,"settingEncodeUrl":true,"settingFollowRedirects":"global","settingRebuildPath":true,"settingSendCookies":true,"settingStoreCookies":true,"url":"{{ Url }}/createlike","_type":"request"},{"_id":"fld_f2bc13ef05c94620a5f27e82b321a135","created":1599628262267,"description":"","environment":{},"environmentPropertyOrder":null,"metaSortKey":-1599628262267,"modified":1599628262267,"name":"LIKE","parentId":"wrk_7dfc9a1ccc774dc5843df14ec83b5272","_type":"request_group"},{"_id":"wrk_7dfc9a1ccc774dc5843df14ec83b5272","created":1598562882654,"description":"","modified":1598562882654,"name":"https://back-apipets.herokuapp.com","parentId":null,"scope":null,"_type":"workspace"},{"_id":"req_88500a1f619f4941afcce9b8648a4e05","authentication":{},"body":{},"created":1599628285655,"description":"","headers":[],"isPrivate":false,"metaSortKey":-1598563163482.5,"method":"GET","modified":1599628361041,"name":"ShowAllLikes","parameters":[],"parentId":"fld_f2bc13ef05c94620a5f27e82b321a135","settingDisableRenderRequestBody":false,"settingEncodeUrl":true,"settingFollowRedirects":"global","settingRebuildPath":true,"settingSendCookies":true,"settingStoreCookies":true,"url":"{{ Url }}/showalllikes","_type":"request"},{"_id":"req_ff463f527c174ce5abb6f225f2df2f0f","authentication":{},"body":{},"created":1599628635293,"description":"","headers":[{"description":"","id":"pair_b76c9b2662a64b00a64d8b38be6b1d43","name":"post_id","value":"5f53a239f130bf002174ddf5"}],"isPrivate":false,"metaSortKey":-1598563163476.25,"method":"GET","modified":1599630707012,"name":"GetLikeCount","parameters":[],"parentId":"fld_f2bc13ef05c94620a5f27e82b321a135","settingDisableRenderRequestBody":false,"settingEncodeUrl":true,"settingFollowRedirects":"global","settingRebuildPath":true,"settingSendCookies":true,"settingStoreCookies":true,"url":"{{ Url }}/getpostlikecount","_type":"request"},{"_id":"req_1adbee1472e3402f97f3f326bb6f4ea0","authentication":{},"body":{},"created":1599628785192,"description":"","headers":[{"description":"","id":"pair_b76c9b2662a64b00a64d8b38be6b1d43","name":"post_id","value":"5f53a239f130bf002174ddf5"}],"isPrivate":false,"metaSortKey":-1598563163473.125,"method":"GET","modified":1599630662553,"name":"GetLikebyPost","parameters":[],"parentId":"fld_f2bc13ef05c94620a5f27e82b321a135","settingDisableRenderRequestBody":false,"settingEncodeUrl":true,"settingFollowRedirects":"global","settingRebuildPath":true,"settingSendCookies":true,"settingStoreCookies":true,"url":"{{ Url }}/getlikebypost","_type":"request"},{"_id":"req_edb40eb37a3248419f0607800d9f75e5","authentication":{},"body":{"mimeType":"multipart/form-data","params":[]},"created":1599317656377,"description":"","headers":[{"deion":"","id":"pair_f508909ae04e4750872fe2f5effc8fd2","name":"message","value":"\"outro user\""},{"deion":"","id":"pair_db66cf5230764ec1997b5baa74393c96","name":"post_id","value":"5f53a239f130bf002174ddf5"},{"description":"","id":"pair_cd612342280a47b290fcf65fd30f204e","name":"token","value":"5f5191422a9c66002141485b"}],"isPrivate":false,"metaSortKey":-1598563163570,"method":"POST","modified":1599627841685,"name":"CreateComment","parameters":[],"parentId":"fld_a37134fef92b44498dda61bd57451cf0","settingDisableRenderRequestBody":false,"settingEncodeUrl":true,"settingFollowRedirects":"global","settingRebuildPath":true,"settingSendCookies":true,"settingStoreCookies":true,"url":"{{ Url }}/createcomment","_type":"request"},{"_id":"fld_a37134fef92b44498dda61bd57451cf0","created":1599317678604,"description":"","environment":{},"environmentPropertyOrder":null,"metaSortKey":-1599317678604,"modified":1599317678604,"name":"COMMENT","parentId":"wrk_7dfc9a1ccc774dc5843df14ec83b5272","_type":"request_group"},{"_id":"req_c16b5a3ccc3e43d4818ac55019549afc","authentication":{},"body":{},"created":1599317701820,"description":"","headers":[{"deion":"","id":"pair_03f037188d4941f1adf3321824dd1cf2","name":"post_id","value":"5f53a239f130bf002174ddf5"}],"isPrivate":false,"metaSortKey":-1598563163520,"method":"GET","modified":1599320709056,"name":"GetCommentbyPostId","parameters":[],"parentId":"fld_a37134fef92b44498dda61bd57451cf0","settingDisableRenderRequestBody":false,"settingEncodeUrl":true,"settingFollowRedirects":"global","settingRebuildPath":true,"settingSendCookies":true,"settingStoreCookies":true,"url":"{{ Url }}/getcommentbypostid","_type":"request"},{"_id":"req_9b64bef4456a489eae1b03df5880e63f","authentication":{},"body":{},"created":1599317833286,"description":"","headers":[],"isPrivate":false,"metaSortKey":-1598563163495,"method":"GET","modified":1599317840905,"name":"ShowAllComments","parameters":[],"parentId":"fld_a37134fef92b44498dda61bd57451cf0","settingDisableRenderRequestBody":false,"settingEncodeUrl":true,"settingFollowRedirects":"global","settingRebuildPath":true,"settingSendCookies":true,"settingStoreCookies":true,"url":"{{ Url }}/showallcomments","_type":"request"},{"_id":"req_76fc1105443746e5abdb27837882510c","authentication":{},"body":{},"created":1599317727579,"description":"","headers":[{"deion":"","id":"pair_669abc3489ba4c609fae9433096d1e70","name":"comment","value":"5f53af7ceb10540021785bb3"},{"deion":"","id":"pair_09389229091440f4aa612b49109e7e8c","name":"token","value":"5f53b319f401fe00214b875c"}],"isPrivate":false,"metaSortKey":-1598563163470,"method":"DELETE","modified":1599625939812,"name":"DeleteComment","parameters":[],"parentId":"fld_a37134fef92b44498dda61bd57451cf0","settingDisableRenderRequestBody":false,"settingEncodeUrl":true,"settingFollowRedirects":"global","settingRebuildPath":true,"settingSendCookies":true,"settingStoreCookies":true,"url":"{{ Url }}/deletecomment","_type":"request"},{"_id":"req_345d32fec57544ae87dd9a607742d872","authentication":{},"body":{"mimeType":"multipart/form-data","params":[{"deion":"","fileName":"C:\\Users\\julia\\Desktop\\perfil-pet-instagram_0.jpg","id":"pair_4a117639850b4adcaea1f2a7bcfb0fd3","name":"picture","type":"file","value":""},{"deion":"","id":"pair_8ada725d69e84221983f375b40b32d89","name":"state","value":"\"lost\""},{"deion":"","id":"pair_b9c066c1c016463e8dcdd41939af3128","name":"deion","value":"\"Cachorrinho encontrado na avenida dos tarumas\""}]},"created":1599253902260,"description":"","headers":[{"deion":"","id":"pair_cdc06f0825a44b9f9f9c12742c9881ba","name":"user_id","value":"5f529f024416a60021528966"},{"deion":"","id":"pair_4e1f1467c6fe49a8ba93c6b2d387ce24","name":"pet_id","value":"5f53a0aef130bf002174ddf4"},{"deion":"","id":"pair_7558224dfa244f898319caafe34d409f","name":"token","value":"5f53b319f401fe00214b875c"}],"isPrivate":false,"metaSortKey":-1598563163495,"method":"POST","modified":1599624471750,"name":"CreatePost","parameters":[],"parentId":"fld_546942ea5494485db0c65625b766d5d4","settingDisableRenderRequestBody":false,"settingEncodeUrl":true,"settingFollowRedirects":"global","settingRebuildPath":true,"settingSendCookies":true,"settingStoreCookies":true,"url":"{{ Url }}/createpost","_type":"request"},{"_id":"fld_546942ea5494485db0c65625b766d5d4","created":1599253890850,"description":"","environment":{},"environmentPropertyOrder":null,"metaSortKey":-1599253890850,"modified":1599624137844,"name":"POST","parentId":"wrk_7dfc9a1ccc774dc5843df14ec83b5272","_type":"request_group"},{"_id":"req_92776105e2aa49b18ebf67d6d18f742f","authentication":{},"body":{},"created":1599253927176,"description":"","headers":[],"isPrivate":false,"metaSortKey":-1598563163445,"method":"GET","modified":1599316821622,"name":"GetPostByState","parameters":[{"deion":"","id":"pair_3d771fb71d4c4437b9d30491a6cedfcf","name":"state","value":"\"lost\""}],"parentId":"fld_546942ea5494485db0c65625b766d5d4","settingDisableRenderRequestBody":false,"settingEncodeUrl":true,"settingFollowRedirects":"global","settingRebuildPath":true,"settingSendCookies":true,"settingStoreCookies":true,"url":"{{ Url }}/getpostbystate","_type":"request"},{"_id":"req_ede2bb8faad340b0ab1033eb451a720c","authentication":{},"body":{},"created":1599624553176,"description":"","headers":[{"deion":"","id":"pair_3c7a1174f6fa4ddea8270d31fb079d93","name":"post","value":"5f53a646b782640021567ff2"},{"deion":"","id":"pair_2caf0a3479fe4a67a86c9807f337fcef","name":"token","value":"5f53b319f401fe00214b875c"}],"isPrivate":false,"metaSortKey":-1598563157314.75,"method":"DELETE","modified":1599624611125,"name":"DeletePost","parameters":[],"parentId":"fld_546942ea5494485db0c65625b766d5d4","settingDisableRenderRequestBody":false,"settingEncodeUrl":true,"settingFollowRedirects":"global","settingRebuildPath":true,"settingSendCookies":true,"settingStoreCookies":true,"url":"{{ Url }}/deletepost","_type":"request"},{"_id":"req_0d9fd38daf034840a460adfef61519ad","authentication":{},"body":{},"created":1599316627460,"description":"","headers":[],"isPrivate":false,"metaSortKey":-1598563151184.5,"method":"GET","modified":1599317609363,"name":"GetPostByUserId","parameters":[{"deion":"","id":"pair_66f2c9f404934de4b7cd2209963c8ee0","name":"user_id","value":"5f529f024416a60021528966"}],"parentId":"fld_546942ea5494485db0c65625b766d5d4","settingDisableRenderRequestBody":false,"settingEncodeUrl":true,"settingFollowRedirects":"global","settingRebuildPath":true,"settingSendCookies":true,"settingStoreCookies":true,"url":"{{ Url }}/getpostbyuserid","_type":"request"},{"_id":"req_5d910ddd42d24622a4b827bc07ad66a2","authentication":{},"body":{},"created":1599254429727,"description":"","headers":[],"isPrivate":false,"metaSortKey":-1598563138924,"method":"GET","modified":1599624743947,"name":"ShowAllPosts","parameters":[],"parentId":"fld_546942ea5494485db0c65625b766d5d4","settingDisableRenderRequestBody":false,"settingEncodeUrl":true,"settingFollowRedirects":"global","settingRebuildPath":true,"settingSendCookies":true,"settingStoreCookies":true,"url":"{{ Url }}/showallposts","_type":"request"},{"_id":"req_fa85ee7675af4495912dbf0e3ff41794","authentication":{},"body":{},"created":1599251217360,"description":"","headers":[],"isPrivate":false,"metaSortKey":-1598563024254,"method":"GET","modified":1599251232845,"name":"ShowAllPets","parameters":[],"parentId":"fld_d18b036b35cc44bd853900ff6e4aa74c","settingDisableRenderRequestBody":false,"settingEncodeUrl":true,"settingFollowRedirects":"global","settingRebuildPath":true,"settingSendCookies":true,"settingStoreCookies":true,"url":"{{ Url }}/showallpets","_type":"request"},{"_id":"fld_d18b036b35cc44bd853900ff6e4aa74c","created":1599251159847,"description":"","environment":{},"environmentPropertyOrder":null,"metaSortKey":-1599251159847,"modified":1599251159847,"name":"PETS","parentId":"wrk_7dfc9a1ccc774dc5843df14ec83b5272","_type":"request_group"},{"_id":"req_b05ab58fe31645359b97e4d9609be5df","authentication":{},"body":{},"created":1599252696776,"description":"","headers":[{"deion":"","id":"pair_3c7a1174f6fa4ddea8270d31fb079d93","name":"pet","value":"5f52b0a97f25bb0021305a2c"},{"deion":"","id":"pair_2caf0a3479fe4a67a86c9807f337fcef","name":"token","value":"5f53b319f401fe00214b875d"}],"isPrivate":false,"metaSortKey":-1598563013905.25,"method":"DELETE","modified":1599623145305,"name":"DeletePet","parameters":[],"parentId":"fld_d18b036b35cc44bd853900ff6e4aa74c","settingDisableRenderRequestBody":false,"settingEncodeUrl":true,"settingFollowRedirects":"global","settingRebuildPath":true,"settingSendCookies":true,"settingStoreCookies":true,"url":"{{ Url }}/deletepet","_type":"request"},{"_id":"req_bd29595ef7da4877b692ad66916cf978","authentication":{},"body":{},"created":1599251977242,"description":"","headers":[{"deion":"","id":"pair_fc4a4a3e48714b09938e96480e5c7dc1","name":"user_id","value":"5f529f024416a60021528966"}],"isPrivate":false,"metaSortKey":-1598563003556.5,"method":"GET","modified":1599254769866,"name":"GetPetByUserId","parameters":[],"parentId":"fld_d18b036b35cc44bd853900ff6e4aa74c","settingDisableRenderRequestBody":false,"settingEncodeUrl":true,"settingFollowRedirects":"global","settingRebuildPath":true,"settingSendCookies":true,"settingStoreCookies":true,"url":"{{ Url }}/getpetbyuserid","_type":"request"},{"_id":"req_e1f38361db1b442982ccc86260df1774","authentication":{},"body":{"mimeType":"multipart/form-data","params":[{"deion":"","fileName":"C:\\Users\\Juliano\\Desktop\\petpicture.jpg","id":"pair_9c32ac9fd769470db2a1124b4ce50356","name":"profilePicture","type":"file","value":""},{"deion":"","id":"pair_a83d4ce9af884508b9a5ae479370a73a","name":"firstName","value":"\"Doguinho2\""},{"deion":"","id":"pair_5a41d5795cdf4f5cb37b261d0509e993","name":"lastName","value":"\"Brancudão\""},{"deion":"","id":"pair_adda518e648742c2a91095cb4fabf4c6","name":"color","value":"\"white\""},{"deion":"","id":"pair_db7e0c75e69d4ba7acb71ff01aa497ee","name":"coatSize","value":"\"small\""},{"deion":"","id":"pair_0566d713dcd34ee3b136874f91feeeae","name":"bithdate","value":"\"21/08/2018\""},{"deion":"","id":"pair_cb16aa24600b47499f1148544153f37b","name":"male","value":"true"}]},"created":1599252116488,"description":"","headers":[{"id":"pair_5e0bbf5a09834e6083a2b40b5d569084","name":"Content-Type","value":"multipart/form-data"},{"deion":"","id":"pair_ebacff356ebf4fd396120febede7ea1b","name":"token","value":"5f52a7b302f2e70021694dec"}],"isPrivate":false,"metaSortKey":-1598562993207.75,"method":"POST","modified":1599316134239,"name":"CreatePet","parameters":[],"parentId":"fld_d18b036b35cc44bd853900ff6e4aa74c","settingDisableRenderRequestBody":false,"settingEncodeUrl":true,"settingFollowRedirects":"global","settingRebuildPath":true,"settingSendCookies":true,"settingStoreCookies":true,"url":"{{ Url }}/createpet","_type":"request"},{"_id":"req_24ff98cd2a05415fb06b8f3c48f981c5","authentication":{},"body":{},"created":1598568116447,"description":"","headers":[{"deion":"","id":"pair_9c3f812cd2a9494f987463718ef29e3a","name":"email","value":"\"abc@hotmail.com\""},{"deion":"","id":"pair_d4f49007287d48f296f05b5a186ba1c4","name":"pass","value":"\"123456\""},{"deion":"","id":"pair_95216fe8dc3d46efb605f65a2b0093ac","name":"fullname","value":"\"Abc Sobrenome1 Sobrenome2\""},{"deion":"","id":"pair_0d4f0a6ea00643b9a3e9b9e09c336b38","name":"male","value":"false"}],"isPrivate":false,"metaSortKey":-1599250114717,"method":"POST","modified":1599250169886,"name":"Create Login","parameters":[],"parentId":"fld_db617a7e886d407b87cce3d8eef6056b","settingDisableRenderRequestBody":false,"settingEncodeUrl":true,"settingFollowRedirects":"global","settingRebuildPath":true,"settingSendCookies":true,"settingStoreCookies":true,"url":"{{ Url }}/createlogin","_type":"request"},{"_id":"fld_db617a7e886d407b87cce3d8eef6056b","created":1599250114667,"description":"","environment":{},"environmentPropertyOrder":null,"metaSortKey":-1599250114667,"modified":1599250114667,"name":"USER","parentId":"wrk_7dfc9a1ccc774dc5843df14ec83b5272","_type":"request_group"},{"_id":"req_00bed6d5105c44c6af296b1bf06e648c","authentication":{},"body":{},"created":1599250219695,"description":"","headers":[{"deion":"","id":"pair_9c3f812cd2a9494f987463718ef29e3a","name":"email","value":"\"abc@hotmail.com\""}],"isPrivate":false,"metaSortKey":-1598906663652,"method":"GET","modified":1599250240923,"name":"GetUserbyEmail","parameters":[],"parentId":"fld_db617a7e886d407b87cce3d8eef6056b","settingDisableRenderRequestBody":false,"settingEncodeUrl":true,"settingFollowRedirects":"global","settingRebuildPath":true,"settingSendCookies":true,"settingStoreCookies":true,"url":"{{ Url }}/getuserbyemail","_type":"request"},{"_id":"req_32cfb97714784ab3bc2260e673fe9d12","authentication":{},"body":{},"created":1599250256148,"description":"","headers":[{"deion":"","id":"pair_541674f32ee4469bb2ca249706da334a","name":"","value":""}],"isPrivate":false,"metaSortKey":-1598734938119.5,"method":"GET","modified":1599250361703,"name":"ShowAllUsers","parameters":[],"parentId":"fld_db617a7e886d407b87cce3d8eef6056b","settingDisableRenderRequestBody":false,"settingEncodeUrl":true,"settingFollowRedirects":"global","settingRebuildPath":true,"settingSendCookies":true,"settingStoreCookies":true,"url":"{{ Url }}/showallusers","_type":"request"},{"_id":"req_73aff066e36a45448e3b330b44ad37b5","authentication":{},"body":{},"created":1599250295787,"description":"","headers":[{"deion":"","id":"pair_4bd38aba07584bf1a8bcafcff8a7fae1","name":"user_id","value":"5f529f024416a60021528966"}],"isPrivate":false,"metaSortKey":-1598649075353.25,"method":"GET","modified":1599320831882,"name":"GetUserbyId","parameters":[],"parentId":"fld_db617a7e886d407b87cce3d8eef6056b","settingDisableRenderRequestBody":false,"settingEncodeUrl":true,"settingFollowRedirects":"global","settingRebuildPath":true,"settingSendCookies":true,"settingStoreCookies":true,"url":"{{ Url }}/getuserbyid","_type":"request"},{"_id":"req_d8bf8624edb94f849405003c46896111","authentication":{},"body":{},"created":1599250650533,"description":"","headers":[{"deion":"","id":"pair_669abc3489ba4c609fae9433096d1e70","name":"email","value":"\"juliano.sousa@unemat.br\""}],"isPrivate":false,"metaSortKey":-1598606143970.125,"method":"DELETE","modified":1599250703210,"name":"DeleteUserbyEmail","parameters":[],"parentId":"fld_db617a7e886d407b87cce3d8eef6056b","settingDisableRenderRequestBody":false,"settingEncodeUrl":true,"settingFollowRedirects":"global","settingRebuildPath":true,"settingSendCookies":true,"settingStoreCookies":true,"url":"{{ Url }}/deleteuserbyemail","_type":"request"},{"_id":"req_12f0f2ce004c4660b75f7fcf97f536a7","authentication":{},"body":{},"created":1599250727896,"description":"","headers":[{"deion":"","id":"pair_669abc3489ba4c609fae9433096d1e70","name":"user_id","value":"5f497141be9eb200216f413a"}],"isPrivate":false,"metaSortKey":-1598584678278.5625,"method":"DELETE","modified":1599250957928,"name":"DeleteUserbyId","parameters":[],"parentId":"fld_db617a7e886d407b87cce3d8eef6056b","settingDisableRenderRequestBody":false,"settingEncodeUrl":true,"settingFollowRedirects":"global","settingRebuildPath":true,"settingSendCookies":true,"settingStoreCookies":true,"url":"{{ Url }}/deleteuserbyid","_type":"request"},{"_id":"req_abf0e4a23b034aa1bbaeea0a922a9b4f","authentication":{},"body":{},"created":1598563212587,"description":"","headers":[{"id":"pair_f00e95bde1cb49d99774f54967059599","name":"email","value":"\"abc@hotmail.com\""},{"id":"pair_ef0cc379f6a2430284f2aba2178054a0","name":"pass","value":"\"123456\""}],"isPrivate":false,"metaSortKey":-1598563212587,"method":"POST","modified":1599320854982,"name":"CreateAuth","parameters":[],"parentId":"wrk_7dfc9a1ccc774dc5843df14ec83b5272","settingDisableRenderRequestBody":false,"settingEncodeUrl":true,"settingFollowRedirects":"global","settingRebuildPath":true,"settingSendCookies":true,"settingStoreCookies":true,"url":"{{ Url }}/createauth","_type":"request"},{"_id":"req_b38bac67ae3e42b790b07b060f63f23e","authentication":{},"body":{},"created":1598563114403,"description":"","headers":[],"isPrivate":false,"metaSortKey":-1598563114403,"method":"GET","modified":1598563127088,"name":"ConfirmAuth","parameters":[],"parentId":"wrk_7dfc9a1ccc774dc5843df14ec83b5272","settingDisableRenderRequestBody":false,"settingEncodeUrl":true,"settingFollowRedirects":"global","settingRebuildPath":true,"settingSendCookies":true,"settingStoreCookies":true,"url":"{{ Url }}/confirmauth","_type":"request"},{"_id":"req_ac399d207f5b45ed8c5e4d7395786d37","authentication":{},"body":{},"created":1598563065649,"description":"","headers":[],"isPrivate":false,"metaSortKey":-1598563065649,"method":"GET","modified":1598563089352,"name":"ShowAllSession","parameters":[],"parentId":"wrk_7dfc9a1ccc774dc5843df14ec83b5272","settingDisableRenderRequestBody":false,"settingEncodeUrl":true,"settingFollowRedirects":"global","settingRebuildPath":true,"settingSendCookies":true,"settingStoreCookies":true,"url":"{{ Url }}/showsessions","_type":"request"},{"_id":"req_61b3d612d6684576a356a60a9981efb3","authentication":{},"body":{},"created":1598568275166,"description":"","headers":[],"isPrivate":false,"metaSortKey":-1598562982859,"method":"GET","modified":1598568282362,"name":"Show All Users","parameters":[],"parentId":"wrk_7dfc9a1ccc774dc5843df14ec83b5272","settingDisableRenderRequestBody":false,"settingEncodeUrl":true,"settingFollowRedirects":"global","settingRebuildPath":true,"settingSendCookies":true,"settingStoreCookies":true,"url":"{{ Url }}/showallusers","_type":"request"},{"_id":"req_3b9898a86428423bb142432cbc91e1d3","authentication":{},"body":{},"created":1598562900069,"description":"","headers":[],"isPrivate":false,"metaSortKey":-1598562900069,"method":"GET","modified":1599623158091,"name":"GetTrue","parameters":[],"parentId":"wrk_7dfc9a1ccc774dc5843df14ec83b5272","settingDisableRenderRequestBody":false,"settingEncodeUrl":true,"settingFollowRedirects":"global","settingRebuildPath":true,"settingSendCookies":true,"settingStoreCookies":true,"url":"{{ Url }}/gettrue","_type":"request"},{"_id":"env_62756c811ddd06242b200b97e494d90584592c24","color":null,"created":1598562882827,"data":{"Url":"http://localhost:3000"},"dataPropertyOrder":{"&":["Url"]},"isPrivate":false,"metaSortKey":1598562882827,"modified":1599623202586,"name":"Base Environment","parentId":"wrk_7dfc9a1ccc774dc5843df14ec83b5272","_type":"environment"},{"_id":"jar_62756c811ddd06242b200b97e494d90584592c24","cookies":[],"created":1598562882838,"modified":1598562882838,"name":"Default Jar","parentId":"wrk_7dfc9a1ccc774dc5843df14ec83b5272","_type":"cookie_jar"},{"_id":"spc_f9dd1e2e524341be88494bbd5296da4b","contentType":"yaml","contents":"","created":1598562882669,"fileName":"https://back-apipets.herokuapp.com","modified":1598562882669,"parentId":"wrk_7dfc9a1ccc774dc5843df14ec83b5272","_type":"api_spec"}]}